RPi/GPIO.py
RPi/__init__.py
fakeRPiGPIO-1.0.0.dist-info/LICENSE.md
fakeRPiGPIO-1.0.0.dist-info/METADATA
fakeRPiGPIO-1.0.0.dist-info/WHEEL
fakeRPiGPIO-1.0.0.dist-info/top_level.txt
fakeRPiGPIO-1.0.0.dist-info/RECORD
