Metadata-Version: 2.1
Name: fakeRPiGPIO
Version: 1.0.0
Summary: fakeRPiGPIO is a package to simulate the RPi.GPIO package
Home-page: https://github.com/luxedo/fakeRPiGPIO
Author: Luiz Eduardo Amaral
Author-email: luizamaral306@gmail.com
License: GPL3
Keywords: RPi fake GPIO
Platform: UNKNOWN
Classifier: Development Status :: 5 - Production/Stable
Classifier: Intended Audience :: Developers
Classifier: Topic :: System :: Hardware
Classifier: Topic :: Software Development :: Libraries :: Python Modules
Classifier: License :: OSI Approved :: GNU General Public License v3 or later (GPLv3+)
Classifier: Programming Language :: Python :: 3
